topsis/topsis.py
topsis_pragati_102303310-1.0.0.dist-info/METADATA
topsis_pragati_102303310-1.0.0.dist-info/WHEEL
topsis_pragati_102303310-1.0.0.dist-info/entry_points.txt
topsis_pragati_102303310-1.0.0.dist-info/top_level.txt
topsis_pragati_102303310-1.0.0.dist-info/RECORD
