Metadata-Version: 2.4
Name: Topsis-Pragati-102303310
Version: 1.0.0
Summary: A Python package for TOPSIS decision making
Author: Pragati Arora
Requires-Dist: pandas
Requires-Dist: numpy
Dynamic: author
Dynamic: description
Dynamic: description-content-type
Dynamic: requires-dist
Dynamic: summary
